{"solution_0001-0100_027 - remove element.md":"b0254e4b","solution_0001-0100_098 - validate binary search tree.md":"3f9b2f0b","index.md":"c627bb52","solution_0001-0100_001 - two sum.md":"808a62aa","solution_0001-0100_002 - add two numbers.md":"def23857","solution_0001-0100_004 - median of two sorted arrays.md":"1bc84fe8","solution_0001-0100_007 - reverse integer.md":"27fa90b1","solution_0001-0100_009 - palindrome number.md":"d5c352da","solution_0001-0100_013 - roman to integer.md":"00dba9ab","solution_0001-0100_026 - remove duplicates from sorted array.md":"24b19459","solution_0501-0600_516 - longest palindromic subsequence.md":"0a6130bc","solution_0501-0600_518 - coin change 2.md":"12add1f4","solution_0501-0600_541 - reverse string ii.md":"d72ffe1f","solution_0501-0600_543 - diameter of binary tree.md":"6f10c7e9","solution_0601-0700_653 - two sum iv - input is a bst.md":"19b39b7c","solution_0701-0800_704 - binary search.md":"797369de","solution_0701-0800_739 - daily temperatures.md":"2287b4a3","solution_0701-0800_771 - jewels and stones.md":"bbf0d810","solution_0001-0100_024 - swap nodes in pairs.md":"42150ff7","solution_0401-0500_442 - find all duplicates in an array.md":"4ed2d3aa","solution_0001-0100_037 - sudoku solver.md":"339bbd39","solution_0001-0100_051 - n-queens.md":"887fbce0","solution_0001-0100_055 - jump game.md":"b60765ec","solution_0001-0100_058 - length of last word.md":"95cce79a","solution_0001-0100_061 - rotate list .md":"b2d57b86","solution_0001-0100_070 - climbing stairs.md":"198d824c","solution_0001-0100_072 - edit distance.md":"8ed7582d","solution_0001-0100_075 - sort colors.md":"d8227574","topicwise.md":"bc3eb0a5","solution_0101-0200_104 - maximum depth of binary tree.md":"3ac37c9a","solution_0101-0200_110 - balanced binary tree.md":"78d0ab7f","solution_0101-0200_111 - minimum depth of binary tree.md":"86102dc9","solution_0101-0200_122 - best time to buy and sell stock ii.md":"f421fdfe","solution_0101-0200_144 - binary tree preorder traversal.md":"127dfc88","solution_0101-0200_145 - binary tree postorder traversal.md":"6dee9dd2","serialwise.md":"2e7fe1c9","solution_0101-0200_172 - factorial trailing zeroes.md":"5679e58c","solution_0101-0200_191 - number of 1 bits.md":"5b02e166","solution_0101-0200_199 - binary tree right side view.md":"452f95a2","solution_0201-0300_206 - reverse linked list.md":"912e5ae2","solution_0201-0300_222 - count complete tree nodes.md":"89b7cc16","solution_0201-0300_230 - kth smallest element in a bst.md":"6ef69648","solution_0201-0300_231 - power of two.md":"8ff7bda9","solution_0201-0300_278 - first bad version.md":"bad1d315","solution_0201-0300_283 - move zeroes.md":"6c38fd6e","solution_0201-0300_300 - longest increasing subsequence.md":"b6ab16ff","solution_0301-0400_322 - coin change.md":"c66ebb18","solution_0301-0400_337 - house robber iii.md":"cb60b996","solution_0301-0400_344 - reverse string.md":"72a2200e","solution_0301-0400_367 - valid perfect square.md":"524183f6","solution_0301-0400_369 - plus one linked list.md":"ba7f5de2","solution_0301-0400_389 - find the difference.md":"98a6d854","solution_0001-0100_094 - binary tree inorder traversal.md":"5f3d63cd","solution_0001-0100_100 - same tree.md":"bbd069d9","solution_0101-0200_103 - binary tree zigzag level order traversal.md":"a60feb49","solution_0401-0500_445 - add two numbers ii.md":"6d3bc3b7","solution_0501-0600_506 -  relative ranks.md":"f6620838","solution_0501-0600_509 - fibonacci number.md":"fbb1f9e2","solution_0801-0900_876 - middle of the linked list.md":"ebd09975","solution_0801-0900_888 - fair candy swap.md":"39797507","solution_1001-1100_1047 - remove all adjacent duplicates in string.md":"f2d64796","solution_1001-1100_1092 - shortest common supersequence.md":"e6a9d5c0","solution_1101-1200_1143 - longest common subsequence.md":"8fd3597b","solution_1201-1300_1232 - check if it is a straight line.md":"0293fe30","solution_1401-1500_1461 - check if a string contains all binary codes of size k.md":"64187a68","solution_1401-1500_1480 - running sum of 1d array.md":"683e7ecb","solution_1401-1500_1491 - average salary excluding the minimum and maximum salary.md":"d736466f","solution_1401-1500_1498 - number of subsequences that satisfy the given sum condition.md":"84b975bc","solution_1501-1600_1537 - get the maximum score.md":"ac4f6cef","solution_2201-2300_2236 - root equals sum of children.md":"0a203de0"}
